.hgignore
.hgtags
CHANGES.txt
README.txt
bootstrap.py
buildout.cfg
setup.py
src/nagios/__init__.py
src/nagios.responsetime.egg-info/PKG-INFO
src/nagios.responsetime.egg-info/SOURCES.txt
src/nagios.responsetime.egg-info/dependency_links.txt
src/nagios.responsetime.egg-info/entry_points.txt
src/nagios.responsetime.egg-info/namespace_packages.txt
src/nagios.responsetime.egg-info/not-zip-safe
src/nagios.responsetime.egg-info/requires.txt
src/nagios.responsetime.egg-info/top_level.txt
src/nagios/responsetime/__init__.py
src/nagios/responsetime/check.py
src/nagios/responsetime/logfile.py
src/nagios/responsetime/util.py
src/nagios/responsetime/tests/__init__.py
src/nagios/responsetime/tests/test_check.py
src/nagios/responsetime/tests/test_logfile.py
src/nagios/responsetime/tests/fixtures/example.log