Metadata-Version: 1.0
Name: nagios.responsetime
Version: 1.0.2
Summary: A Nagios plugin that collects response times from logs.
Home-page: http://pypi.python.org/pypi/nagios.responsetime
Author: gocept
Author-email: mail@gocept.com
License: ZPL 2.1
Platform: UNKNOWN
